README.rst
flake8chart.py
setup.py
flake8_chart.egg-info/PKG-INFO
flake8_chart.egg-info/SOURCES.txt
flake8_chart.egg-info/dependency_links.txt
flake8_chart.egg-info/entry_points.txt
flake8_chart.egg-info/not-zip-safe
flake8_chart.egg-info/requires.txt
flake8_chart.egg-info/top_level.txt