Metadata-Version: 1.1
Name: flake8-chart
Version: 0.1.3
Summary: flake8 stats visualised
Home-page: https://github.com/microamp/flake8-chart
Author: james sangho nah
Author-email: sangho.nah@gmail.com
License: MIT License
Platform: UNKNOWN
Classifier: Development Status :: 2 - Pre-Alpha
Classifier: Intended Audience :: Developers
Classifier: License :: OSI Approved :: MIT License
Classifier: Operating System :: OS Independent
Classifier: Programming Language :: Python
Classifier: Programming Language :: Python :: 2.7
Classifier: Programming Language :: Python :: 3.4
Classifier: Topic :: Software Development :: Quality Assurance
